LICENSE
MANIFEST.in
README.md
setup.py
django_simple_api_key.egg-info/PKG-INFO
django_simple_api_key.egg-info/SOURCES.txt
django_simple_api_key.egg-info/dependency_links.txt
django_simple_api_key.egg-info/requires.txt
django_simple_api_key.egg-info/top_level.txt
simple_api_key/__init__.py
simple_api_key/admin.py
simple_api_key/decorators.py
simple_api_key/models.py
simple_api_key/views.py