Metadata-Version: 1.1
Name: django-simple-api-key
Version: 0.1.0
Summary: A simple Django app to provide users api keys.
Home-page: https://github.com/CIGIHub/django-simple-api-key/
Author: Caroline Simpson
Author-email: csimpson@cigionline.org
License: MIT License
Platform: UNKNOWN
Classifier: Environment :: Web Environment
Classifier: Framework :: Django
Classifier: Intended Audience :: Developers
Classifier: License :: OSI Approved :: MIT License
Classifier: Operating System :: OS Independent
Classifier: Programming Language :: Python
Classifier: Programming Language :: Python :: 2
Classifier: Topic :: Internet :: WWW/HTTP
Classifier: Topic :: Internet :: WWW/HTTP :: Dynamic Content
Requires: south (>= 0.8.1)
